boop/__init__.py
boop/boop.py
boop/boop_utils/__init__.py
boop/boop_utils/boop_utils.py
boop-1.0.5.dist-info/METADATA
boop-1.0.5.dist-info/WHEEL
boop-1.0.5.dist-info/top_level.txt
boop-1.0.5.dist-info/RECORD
