Metadata-Version: 2.1
Name: boop
Version: 1.0.5
Summary: A brief description of your library
Author: Your Name
Author-email: your.email@example.com
Classifier: License :: OSI Approved :: MIT License
Classifier: Programming Language :: Python :: 3
